libreria_otaku/__init__.py
libreria_otaku/libreria_otaku.py
libreria_otaku-0.1.0.dist-info/METADATA
libreria_otaku-0.1.0.dist-info/WHEEL
libreria_otaku-0.1.0.dist-info/top_level.txt
libreria_otaku-0.1.0.dist-info/RECORD
